README.md
bgconfig.py
setup.cfg
setup.py
bgconfig.egg-info/PKG-INFO
bgconfig.egg-info/SOURCES.txt
bgconfig.egg-info/dependency_links.txt
bgconfig.egg-info/requires.txt
bgconfig.egg-info/top_level.txt
bgconfig.egg-info/zip-safe