Metadata-Version: 1.1
Name: bgconfig
Version: 0.7.0
Summary: Bgconfig library to manage configuration files.
Home-page: https://bitbucket.org/bgframework/bgconfig
Author: Jordi Deu-Pons
Author-email: jordi.deu@irbbarcelona.org
License: Apache License 2
Download-URL: https://bitbucket.org/bgframework/bgconfig/get/0.7.0.tar.gz
Platform: UNKNOWN
